know_your_exceptions/__init__.py
know_your_exceptions/decorators.py
know_your_exceptions-0.3.dist-info/LICENSE.txt
know_your_exceptions-0.3.dist-info/METADATA
know_your_exceptions-0.3.dist-info/WHEEL
know_your_exceptions-0.3.dist-info/top_level.txt
know_your_exceptions-0.3.dist-info/RECORD
