Metadata-Version: 2.1
Name: know-your-exceptions
Version: 0.3
Summary: Identitfy the exact exception class
Home-page: https://github.com/singhgautam7/Python-GoldMine/tree/master/know_your_exceptions
Author: Gautam Rajeev Singh
Author-email: gautamsingh1997@gmail.com
License: MIT
Keywords: pyton print color styles
Platform: UNKNOWN
Classifier: Programming Language :: Python :: 3
Classifier: License :: OSI Approved :: MIT License
Classifier: Operating System :: OS Independent
Requires-Python: >=3.0
License-File: LICENSE.txt
